amIFat/__init__.py
amIFat/__main__.py
amIFat/calories.py
amIFat/fat_problems.py
amIFat/howfat.py
amIFat/macros.py
amIFatApp/app.py
amIFat-1.1.0.dist-info/LICENSE
amIFat-1.1.0.dist-info/METADATA
amIFat-1.1.0.dist-info/WHEEL
amIFat-1.1.0.dist-info/top_level.txt
amIFat-1.1.0.dist-info/RECORD
