Metadata-Version: 2.1
Name: amIFat
Version: 1.1.0
Summary: An example of a package developed with pyenv, built with build using setuptools, uploaded to PyPI using twine, and distributed via pip.
Author-email: bhavig <bob@hamsterdam.com>, brian <brian@lee.com>, misha <misha@seo.com>, sangybaek <sang@ybaek.com>
License: GNU GENERAL PUBLIC LICENSE
Project-URL: Homepage, https://github.com/software-students-fall2022/python-package-exercise-project-3-team-17
Project-URL: Repository, https://github.com/software-students-fall2022/python-package-exercise-project-3-team-17.git
Project-URL: Bug Tracker, https://github.com/software-students-fall2022/python-package-exercise-project-3-team-17/issues
Keywords: python,package,build,fitness
Classifier: Programming Language :: Python :: 3
Classifier: Intended Audience :: Education
Classifier: License :: OSI Approved :: GNU General Public License v3 (GPLv3)
Classifier: Operating System :: OS Independent
Requires-Python: >=3.7
License-File: LICENSE
Provides-Extra: dev
Requires-Dist: pytest ; extra == 'dev'
